[
    {
        "en": "pale",
        "zh": "苍白"
    },
    {
        "en": "fair",
        "zh": "公平的"
    },
    {
        "en": "light",
        "zh": "光"
    },
    {
        "en": "olive",
        "zh": "橄榄"
    },
    {
        "en": "tan",
        "zh": "棕褐色"
    },
    {
        "en": "golden",
        "zh": "金的"
    },
    {
        "en": "honey",
        "zh": "蜂蜜"
    },
    {
        "en": "bronze",
        "zh": "青铜"
    },
    {
        "en": "brown",
        "zh": "棕色的"
    },
    {
        "en": "dark brown",
        "zh": "深棕色"
    },
    {
        "en": "chocolate",
        "zh": "巧克力"
    },
    {
        "en": "ebony",
        "zh": "乌木"
    },
    {
        "en": "ivory",
        "zh": "象牙"
    },
    {
        "en": "peach",
        "zh": "桃"
    },
    {
        "en": "rosy",
        "zh": "红润"
    },
    {
        "en": "alabaster",
        "zh": "雪花石膏"
    },
    {
        "en": "ashen",
        "zh": "铁青"
    },
    {
        "en": "caramel",
        "zh": "焦糖"
    },
    {
        "en": "cocoa",
        "zh": "可可"
    },
    {
        "en": "mahogany",
        "zh": "桃花心木"
    },
    {
        "en": "sienna",
        "zh": "赭色"
    },
    {
        "en": "mocha",
        "zh": "摩卡"
    },
    {
        "en": "coffee",
        "zh": "咖啡"
    },
    {
        "en": "walnut",
        "zh": "核桃"
    },
    {
        "en": "porcelain",
        "zh": "瓷"
    },
    {
        "en": "wheatish",
        "zh": "小麦色"
    },
    {
        "en": "ruddy",
        "zh": "红润"
    },
    {
        "en": "freckled",
        "zh": "有雀斑的"
    },
    {
        "en": "blemished",
        "zh": "有瑕疵"
    },
    {
        "en": "rosy-cheeked",
        "zh": "红润的"
    },
    {
        "en": "sun-kissed",
        "zh": "阳光普照"
    },
    {
        "en": "weathered",
        "zh": "风化"
    },
    {
        "en": "flawless",
        "zh": "完美无瑕"
    },
    {
        "en": "smooth",
        "zh": "光滑的"
    },
    {
        "en": "rough",
        "zh": "粗糙的"
    }
]